grassland_production/__init__.py
grassland_production/database/__init__.py
grassland_production/database/grassland_management_database.db
grassland_production/dry_matter.py
grassland_production/farm_data_generation.py
grassland_production/fertilisation.py
grassland_production/geo_grassland_production/__init__.py
grassland_production/geo_grassland_production/catchment_grassland.py
grassland_production/geo_grassland_production/geo_dry_matter.py
grassland_production/geo_grassland_production/geo_farm_data_generation.py
grassland_production/geo_grassland_production/geo_fertilisation.py
grassland_production/geo_grassland_production/geo_grass_yield.py
grassland_production/geo_grassland_production/geo_grassland_output.py
grassland_production/geo_grassland_production/geo_grassland_soils.py
grassland_production/geo_grassland_production/geo_spared_area.py
grassland_production/geo_grassland_production/geo_stocking_rate.py
grassland_production/geo_grassland_production/geo_utilisation_rate.py
grassland_production/grass_yield.py
grassland_production/grassland_area.py
grassland_production/grassland_output.py
grassland_production/grassland_soils.py
grassland_production/resource_manager/__init__.py
grassland_production/resource_manager/data_loader.py
grassland_production/resource_manager/database_manager.py
grassland_production/resource_manager/grassland_data_manager.py
grassland_production/resource_manager/scenario_data_fetcher.py
grassland_production/spared_area.py
grassland_production/stocking_rate.py
grassland_production/utilisation_rate.py
grassland_production-0.3.6.dist-info/LICENSE
grassland_production-0.3.6.dist-info/METADATA
grassland_production-0.3.6.dist-info/WHEEL
grassland_production-0.3.6.dist-info/RECORD
