Metadata-Version: 2.1
Name: grassland_production
Version: 0.3.6
Summary: Computation of grassland area and production based on animal energy calculations and grassland inputs
License: MIT
Author: Colm Duffy
Requires-Python: >=3.9,<4.0
Classifier: License :: OSI Approved :: MIT License
Classifier: Programming Language :: Python :: 3
Classifier: Programming Language :: Python :: 3.9
Classifier: Programming Language :: Python :: 3.10
Classifier: Programming Language :: Python :: 3.11
Classifier: Programming Language :: Python :: 3.12
Requires-Dist: catchment_data_api (>=0.1.0,<0.2.0)
Requires-Dist: cattle_lca (==0.3.1)
Requires-Dist: numpy (>=1.25.0,<2.0.0)
Requires-Dist: pandas (==2.1.4)
Requires-Dist: sheep_lca (==0.3.1)
Requires-Dist: sqlalchemy (<2.0)
